{
  "updated_at": "2026-03-12T21:59:33.559262",
  "mode": "paper",
  "kill_switch": false,
  "circuit_breaker_active": false,
  "equity": 10000,
  "balance": 9600.0,
  "open_positions": 2,
  "realized_pnl": 0,
  "unrealized_pnl": -0.22,
  "daily_pnl": 0,
  "win_rate": 0,
  "total_trades": 0,
  "daily_trades": 2,
  "max_drawdown": 0,
  "avg_win": 0,
  "avg_loss": 0,
  "avg_rr": 0,
  "profit_factor": 0,
  "open_risk": 12.0,
  "daily_loss_used": 0,
  "daily_loss_pct": 0.0,
  "daily_loss_limit": 10,
  "consecutive_losses": 0,
  "positions": [
    {
      "id": 1773352695315,
      "symbol": "SOLUSDT",
      "side": "SHORT",
      "entry_price": 86.48,
      "sl_price": 89.07,
      "tp_price": 81.29,
      "position_size": 200.0,
      "qty": 2.312673,
      "estimated_risk": 6.0,
      "confidence": 11.77,
      "reason": "Moderate momentum: -1.18% in 24h. Continuation pla",
      "strategy": "momentum",
      "status": "open",
      "stop_status": "protected",
      "opened_at": "2026-03-12T21:58:15.315481",
      "closed_at": null,
      "pnl": 0,
      "exit_reason": null,
      "slippage": 0
    },
    {
      "id": 1773352695479,
      "symbol": "BTCUSDT",
      "side": "SHORT",
      "entry_price": 70294.0,
      "sl_price": 72402.82,
      "tp_price": 66076.36,
      "position_size": 200.0,
      "qty": 0.002845,
      "estimated_risk": 6.0,
      "confidence": 5.71,
      "reason": "Weak momentum: -0.57% in 24h. Early entry attempt.",
      "strategy": "momentum",
      "status": "open",
      "stop_status": "protected",
      "opened_at": "2026-03-12T21:58:15.479319",
      "closed_at": null,
      "pnl": 0,
      "exit_reason": null,
      "slippage": 0
    }
  ],
  "prices": {
    "BTCUSDT": {
      "price": 70296.9,
      "change_pct": -0.544,
      "volume": 17453.291
    },
    "ETHUSDT": {
      "price": 2063.1,
      "change_pct": -0.401,
      "volume": 329649.246
    },
    "SOLUSDT": {
      "price": 86.57,
      "change_pct": -0.995,
      "volume": 1437761.63
    }
  },
  "last_price_update": "2026-03-12T21:59:33.551190",
  "exchange_status": "connected",
  "data_status": "live",
  "sync_status": "synced",
  "errors": [],
  "pnl_by_symbol": {},
  "last_20_trades": [],
  "signal_candidates": [
    {
      "timestamp": "2026-03-12T21:59:33.553760",
      "symbol": "BTCUSDT",
      "side": "SHORT",
      "price": 70296.9,
      "confidence": 5.44,
      "change_pct": -0.544,
      "regime": "range",
      "explanation": "Weak momentum: -0.54% in 24h. Early entry attempt.",
      "block_reason": null
    },
    {
      "timestamp": "2026-03-12T21:59:33.553823",
      "symbol": "SOLUSDT",
      "side": "SHORT",
      "price": 86.57,
      "confidence": 9.95,
      "change_pct": -0.995,
      "regime": "range",
      "explanation": "Weak momentum: -0.99% in 24h. Early entry attempt.",
      "block_reason": null
    }
  ],
  "blocked_signals": [
    {
      "timestamp": "2026-03-12T21:59:33.553810",
      "symbol": "ETHUSDT",
      "side": "SHORT",
      "price": 2063.1,
      "confidence": 4.01,
      "change_pct": -0.401,
      "regime": "range",
      "explanation": "No momentum: -0.40% in 24h. Below threshold.",
      "block_reason": "Confidence 4% < threshold 5%"
    },
    {
      "timestamp": "2026-03-12T21:59:33.555100",
      "symbol": "BTCUSDT",
      "side": "SHORT",
      "confidence": 5.44,
      "block_reason": "Position already open",
      "explanation": "Weak momentum: -0.54% in 24h. Early entry attempt."
    },
    {
      "timestamp": "2026-03-12T21:59:33.556967",
      "symbol": "SOLUSDT",
      "side": "SHORT",
      "confidence": 9.95,
      "block_reason": "Position already open",
      "explanation": "Weak momentum: -0.99% in 24h. Early entry attempt."
    }
  ]
}