{
  "updated_at": "2026-03-12T20:40:55.007223",
  "equity": 10012.25,
  "open_positions": 2,
  "total_pnl": 12.25,
  "win_rate": 100.0,
  "total_trades": 1,
  "positions": [
    {
      "id": 1773345800000,
      "symbol": "BTCUSDT",
      "side": "LONG",
      "entry_price": 70440.2,
      "sl_price": 68327.0,
      "tp_price": 74666.6,
      "position_size": 200.0,
      "confidence": 85.0,
      "reason": "Test trade for dashboard",
      "strategy": "momentum",
      "dca_layers": 1,
      "parent_trade": null,
      "status": "open",
      "opened_at": "2026-03-12T20:01:00",
      "closed_at": null,
      "pnl": 0,
      "exit_reason": null
    },
    {
      "id": 1773345820000,
      "symbol": "ETHUSDT",
      "side": "SHORT",
      "entry_price": 2065.5,
      "sl_price": 2127.5,
      "tp_price": 2001.8,
      "position_size": 200.0,
      "confidence": 75.0,
      "reason": "Test trade for dashboard",
      "strategy": "momentum",
      "dca_layers": 1,
      "parent_trade": null,
      "status": "open",
      "opened_at": "2026-03-12T20:01:20",
      "closed_at": null,
      "pnl": 0,
      "exit_reason": null
    }
  ],
  "prices": {
    "ETHUSDT": {
      "price": 2061.9,
      "change_pct": -0.348,
      "volume": 329598.687
    },
    "SOLUSDT": {
      "price": 86.49,
      "change_pct": -0.712,
      "volume": 1436693.82
    },
    "BTCUSDT": {
      "price": 70166.8,
      "change_pct": -0.43,
      "volume": 17705.138
    }
  }
}