{
  "timestamp": "2026-03-15T13:06:33.033723",
  "equity": 10195.36,
  "unrealized_pnl": -741.06,
  "realized_pnl": 195.36,
  "total_pnl": -545.7,
  "open_positions": 47,
  "long_layers": 10,
  "short_layers": 37,
  "daily_drawdown": -0.09,
  "strategy": "DCA Dual Long + Short - Strategy 2",
  "mode": "paper",
  "prices": {
    "BTCUSDT": 71597.5,
    "ETHUSDT": 2109.4,
    "SOLUSDT": 88.19,
    "BNBUSDT": 662.3,
    "XAUUSDT": 5014.71,
    "HYPEUSDT": 37.387,
    "DOGEUSDT": 0.0964,
    "XRPUSDT": 1.4271,
    "XAGUSDT": 80.57,
    "ADAUSDT": 0.2657,
    "AVAXUSDT": 9.82,
    "DOTUSDT": 1.435,
    "MATICUSDT": 0.413,
    "LINKUSDT": 9.252,
    "LTCUSDT": 55.36,
    "UNIUSDT": 3.983,
    "ATOMUSDT": 1.868,
    "NEARUSDT": 1.352,
    "APTUSDT": 0.934,
    "ARBUSDT": 0.1025
  }
}